SajadEncFree/SajadEncFree.py
SajadEncFree/SajadEncFree_fast.py
SajadEncFree/__init__.py
tests/SajadEncFree_file_test.py
tests/SajadEncFree_test.py
tests/__init__.py
tests/generate_old_pickles.py
tests/test_backward_compat.py
tests/testutils.py
SajadEncFree-3.1.0.dist-info/LICENSE
SajadEncFree-3.1.0.dist-info/METADATA
SajadEncFree-3.1.0.dist-info/WHEEL
SajadEncFree-3.1.0.dist-info/top_level.txt
SajadEncFree-3.1.0.dist-info/RECORD
